COPYING
MANIFEST.in
README.rst
setup.py
munnel/__init__.py
munnel.egg-info/PKG-INFO
munnel.egg-info/SOURCES.txt
munnel.egg-info/dependency_links.txt
munnel.egg-info/entry_points.txt
munnel.egg-info/requires.txt
munnel.egg-info/top_level.txt