Metadata-Version: 1.1
Name: munnel
Version: 0.1
Summary: Milter replacing RCTP TO addresses with configured ones
Home-page: https://lab.nexedi.com/vpelletier/python-munnel
Author: Nexedi
Author-email: vincent@nexedi.com
License: GPLv3
Keywords: smtp milter funnel
Platform: any
Classifier: License :: OSI Approved :: GNU Lesser General Public License v3 (LGPLv3)
Classifier: Operating System :: OS Independent
